__init__.py
fmpy/__init__.py
fmpy/client.py
fmpy/urls.py
fmpy/utils.py
fmpy_qi-0.1.7.dist-info/LICENSE
fmpy_qi-0.1.7.dist-info/METADATA
fmpy_qi-0.1.7.dist-info/WHEEL
fmpy_qi-0.1.7.dist-info/top_level.txt
fmpy_qi-0.1.7.dist-info/RECORD
