Metadata-Version: 2.1
Name: fmpy-qi
Version: 0.1.7
Summary: A python wrapper for the Financial Modeling Prep API
Author-email: Nicolas THIERY <nicles.thiery@gmail.com>
Project-URL: Homepage, https://github.com/NicolasThiery/fmpy
Project-URL: Bug Tracker, https://github.com/NicolasThiery/fmpy/issues
Classifier: Programming Language :: Python :: 3
Classifier: License :: OSI Approved :: MIT License
Classifier: Operating System :: OS Independent
Requires-Python: >=3.7
License-File: LICENSE
Requires-Dist: urllib3 (>=1.23)
Requires-Dist: requests (>=2.5.4.1)
Requires-Dist: pandas (>=2.0.0)
